spuring/__init__.py
spuring/__main__.py
spuring/creation.py
spuring/main.py
spuring/template.py
spuring/scripts/pip.py
spuring/scripts/venv.py
spuring/templates/base.toml
spuring/templates/default.toml
spuring/templates/flask.toml
spuring-0.0.4.dist-info/LICENSE.md
spuring-0.0.4.dist-info/METADATA
spuring-0.0.4.dist-info/WHEEL
spuring-0.0.4.dist-info/entry_points.txt
spuring-0.0.4.dist-info/top_level.txt
spuring-0.0.4.dist-info/RECORD
