Metadata-Version: 2.1
Name: spuring
Version: 0.0.4
Summary: Create a project folder. It can be self configurated
Author-email: Tobias Baumgarten <Tobias.b.baumgarten@gmail.com>
Requires-Python: >=3.7
License-File: LICENSE.md
Requires-Dist: Jinja2 (==3.1.2)
